[{"title": "线性代数_第5版_同济大学.pdf", "target": [{"type": "cloudreve", "link": "https://imon.agentwei.cn/#/s/XVHr"}]}, {"title": "线性代数附册学习辅导与习题全解(同济第五版).pdf", "target": [{"type": "cloudreve", "link": "https://imon.agentwei.cn/#/s/MGsn"}]}, {"title": "线性代数课件.rar", "target": [{"type": "cloudreve", "link": "https://imon.agentwei.cn/#/s/OVTg"}]}, {"title": "新版48课时线性代数课件", "target": [{"type": "cloudreve", "link": "https://imon.agentwei.cn/s/EnjSB"}]}, {"title": "线性代数14-19历年试卷及答案.rar", "target": [{"type": "cloudreve", "link": "https://imon.agentwei.cn/#/s/K5fB"}]}, {"title": "线性代数习题答案.rar", "target": [{"type": "cloudreve", "link": "https://imon.agentwei.cn/#/s/K5fB"}]}, {"title": "2018年后线代试卷", "target": [{"type": "cloudreve", "link": "https://imon.agentwei.cn/s/O8bug"}]}]